qastutil/__init__.py
qastutil/angle.py
qastutil/sky.py
qastutil/sunmoon.py
qastutil-0.32.dist-info/LICENSE
qastutil-0.32.dist-info/METADATA
qastutil-0.32.dist-info/WHEEL
qastutil-0.32.dist-info/top_level.txt
qastutil-0.32.dist-info/RECORD
