Metadata-Version: 2.1
Name: qastutil
Version: 0.32
Summary: Some quick astronomical utility functions.
Home-page: https://gitee.com/drjiezheng/qastutil
Author: Dr Jie Zheng
Author-email: jiezheng@nao.cas.cn
License: MIT
Platform: UNKNOWN
Classifier: Development Status :: 5 - Production/Stable
Classifier: Intended Audience :: Science/Research
Classifier: License :: OSI Approved :: MIT License
Classifier: Operating System :: OS Independent
Classifier: Programming Language :: Python :: 3.7
Classifier: Topic :: Scientific/Engineering :: Physics
Classifier: Topic :: Scientific/Engineering :: Astronomy
Requires: numpy
Requires: datetime
